haprapi/__init__.py
haprapi/client.py
haprapi/config.py
haprapi/models.py
haprapi-0.1.2.dist-info/LICENSE
haprapi-0.1.2.dist-info/METADATA
haprapi-0.1.2.dist-info/WHEEL
haprapi-0.1.2.dist-info/RECORD
