Metadata-Version: 2.1
Name: haprapi
Version: 0.1.2
Summary: A python library for the HAProxy Runtime API
License: GPLv3
Author: Mike Introini
Author-email: michael.introini@gmail.com
Requires-Python: >=3.10,<4.0
Classifier: License :: Other/Proprietary License
Classifier: Programming Language :: Python :: 3
Classifier: Programming Language :: Python :: 3.10
Classifier: Programming Language :: Python :: 3.11
Requires-Dist: pytest (>=8.3.3,<9.0.0)
